dagster_perian/__init__.py
dagster_perian/operations.py
dagster_perian/resources.py
dagster_perian-0.1.1.dist-info/METADATA
dagster_perian-0.1.1.dist-info/WHEEL
dagster_perian-0.1.1.dist-info/RECORD
