Metadata-Version: 2.1
Name: dagster-perian
Version: 0.1.1
Summary: A dagster plugin for the Perian Sky Platform
Home-page: https://perian.io
Keywords: perian,sky,sky-computing,sky-platform,cli
Author: Perian
Author-email: info@perian.io
Requires-Python: >=3.10,<3.13
Classifier: Intended Audience :: Developers
Classifier: Intended Audience :: Science/Research
Classifier: Intended Audience :: System Administrators
Classifier: Programming Language :: Python :: 3
Classifier: Programming Language :: Python :: 3.10
Classifier: Programming Language :: Python :: 3.11
Classifier: Programming Language :: Python :: 3.12
Classifier: Topic :: Scientific/Engineering
Classifier: Topic :: Scientific/Engineering :: Artificial Intelligence
Classifier: Topic :: Software Development
Classifier: Topic :: System :: Distributed Computing
Classifier: Topic :: System :: Systems Administration
Requires-Dist: dagster (>=1.8.10,<2.0.0)
Requires-Dist: dagster-docker (>=0.24.11,<0.25.0)
Requires-Dist: docker (>=7.1.0,<8.0.0)
Requires-Dist: perian (>=0.2.9,<0.3.0)
Project-URL: Documentation, https://perian.io
